stura_voting_utils/__init__.py
stura_voting_utils/parser.py
stura_voting_utils/utils.py
stura_voting_utils/voting.py
stura_voting_utils-0.1.4.dist-info/METADATA
stura_voting_utils-0.1.4.dist-info/RECORD
stura_voting_utils-0.1.4.dist-info/WHEEL
stura_voting_utils-0.1.4.dist-info/top_level.txt
